canvas_cli/__init__.py
canvas_cli/canvas_cli.py
canvas_cli-1.3.4.dist-info/entry_points.txt
canvas_cli-1.3.4.dist-info/WHEEL
canvas_cli-1.3.4.dist-info/METADATA
canvas_cli-1.3.4.dist-info/RECORD
